ose_cli/__init__.py
ose_cli/externals.py
ose_cli/main.py
ose_cli/release.py
ose_cli-0.3.0.dist-info/METADATA
ose_cli-0.3.0.dist-info/WHEEL
ose_cli-0.3.0.dist-info/entry_points.txt
ose_cli-0.3.0.dist-info/top_level.txt
ose_cli-0.3.0.dist-info/RECORD
