Metadata-Version: 2.4
Name: ose-cli
Version: 0.3.0
Summary: CLI for OntoSpreadEd - Ontology spreadsheet editor
Requires-Python: >=3.12
Requires-Dist: ose-core==0.3.0
Requires-Dist: Flask==2.3.3
Requires-Dist: Flask-Injector
Requires-Dist: click>=8.0
Provides-Extra: dev
Requires-Dist: pytest; extra == "dev"
Requires-Dist: ruff; extra == "dev"
